revenium_griptape/__init__.py
revenium_griptape/drivers/__init__.py
revenium_griptape/drivers/revenium_anthropic_driver.py
revenium_griptape/drivers/revenium_litellm_driver.py
revenium_griptape/drivers/revenium_ollama_driver.py
revenium_griptape/drivers/revenium_openai_driver.py
revenium_griptape/drivers/revenium_openai_embedding_driver.py
revenium_griptape/drivers/revenium_universal_driver.py
revenium_griptape-0.1.0.dist-info/licenses/LICENSE
revenium_griptape-0.1.0.dist-info/METADATA
revenium_griptape-0.1.0.dist-info/WHEEL
revenium_griptape-0.1.0.dist-info/top_level.txt
revenium_griptape-0.1.0.dist-info/RECORD
