Metadata-Version: 2.4
Name: revenium-griptape
Version: 0.1.0
Summary: Universal Revenium middleware for Griptape framework - transparent AI usage metering across all providers
Home-page: https://github.com/revenium/revenium-griptape
Author: Revenium
Author-email: Revenium <hello@revenium.io>
License-Expression: MIT
Project-URL: Homepage, https://github.com/revenium/revenium-griptape
Project-URL: Repository, https://github.com/revenium/revenium-griptape
Project-URL: Documentation, https://docs.revenium.io
Project-URL: Bug Tracker, https://github.com/revenium/revenium-griptape/issues
Classifier: Development Status :: 4 - Beta
Classifier: Intended Audience :: Developers
Classifier: Programming Language :: Python :: 3
Classifier: Programming Language :: Python :: 3.8
Classifier: Programming Language :: Python :: 3.9
Classifier: Programming Language :: Python :: 3.10
Classifier: Programming Language :: Python :: 3.11
Classifier: Programming Language :: Python :: 3.12
Classifier: Topic :: Software Development :: Libraries :: Python Modules
Classifier: Topic :: Scientific/Engineering :: Artificial Intelligence
Classifier: Topic :: System :: Monitoring
Requires-Python: >=3.8
License-File: LICENSE
Requires-Dist: griptape>=1.0.0
Requires-Dist: python-dotenv>=0.19.0
Requires-Dist: requests>=2.25.0
Requires-Dist: wrapt>=1.14.0
Provides-Extra: openai
Requires-Dist: revenium-middleware-openai>=0.4.6; extra == "openai"
Requires-Dist: openai>=1.0.0; extra == "openai"
Provides-Extra: anthropic
Requires-Dist: revenium-middleware-anthropic>=0.2.22; extra == "anthropic"
Requires-Dist: anthropic>=0.8.0; extra == "anthropic"
Provides-Extra: ollama
Requires-Dist: revenium-middleware-ollama>=0.1.16; extra == "ollama"
Provides-Extra: litellm
Requires-Dist: revenium-middleware-litellm>=0.1.24; extra == "litellm"
Requires-Dist: litellm>=1.0.0; extra == "litellm"
Provides-Extra: all
Requires-Dist: revenium-middleware-openai>=0.4.6; extra == "all"
Requires-Dist: openai>=1.0.0; extra == "all"
Requires-Dist: revenium-middleware-anthropic>=0.2.22; extra == "all"
Requires-Dist: anthropic>=0.8.0; extra == "all"
Requires-Dist: revenium-middleware-ollama>=0.1.16; extra == "all"
Requires-Dist: revenium-middleware-litellm>=0.1.24; extra == "all"
Requires-Dist: litellm>=1.0.0; extra == "all"
Provides-Extra: dev
Requires-Dist: pytest>=7.0.0; extra == "dev"
Requires-Dist: black>=23.0.0; extra == "dev"
Requires-Dist: flake8>=6.0.0; extra == "dev"
Dynamic: author
Dynamic: home-page
Dynamic: license-file
Dynamic: requires-python
